glidertools/__init__.py
glidertools/_version.py
glidertools/calibration.py
glidertools/cleaning.py
glidertools/flo_functions.py
glidertools/helpers.py
glidertools/mapping.py
glidertools/optics.py
glidertools/physics.py
glidertools/plot.py
glidertools/processing.py
glidertools/utils.py
glidertools/load/__init__.py
glidertools/load/ego.py
glidertools/load/seaglider.py
glidertools/load/slocum.py
glidertools/load/voto_seaexplorer.py
tests/__init__.py
tests/test_calibration.py
tests/test_cleaning.py
tests/test_dive_numbers.py
tests/test_flo_functions.py
tests/test_imports.py
tests/test_load.py
tests/test_mapping.py
tests/test_optics.py
tests/test_physics.py
tests/test_plot.py
tests/test_processing.py
glidertools-2023.7.25.dist-info/LICENSE
glidertools-2023.7.25.dist-info/METADATA
glidertools-2023.7.25.dist-info/WHEEL
glidertools-2023.7.25.dist-info/top_level.txt
glidertools-2023.7.25.dist-info/RECORD
