Metadata-Version: 2.1
Name: glidertools
Version: 2023.7.25
Summary: ("A toolkit for processing Seaglider base station NetCDF files: "
Home-page: https://github.com/GliderToolsCommunity/GliderTools
Author: Luke Gregor
Author-email: "lukegre@gmail.com"
License: GNUv3
Classifier: Development Status :: 3 - Alpha
Classifier: License :: OSI Approved :: MIT License
Classifier: Operating System :: OS Independent
Classifier: Intended Audience :: Science/Research
Classifier: Programming Language :: Python
Classifier: Programming Language :: Python :: 3
Classifier: Programming Language :: Python :: 3.8
Classifier: Programming Language :: Python :: 3.9
Classifier: Programming Language :: Python :: 3.10
Classifier: Programming Language :: Python :: 3.11
Requires-Python: >=3.8
License-File: LICENSE
Requires-Dist: numexpr
Requires-Dist: netcdf4
Requires-Dist: pandas
Requires-Dist: xarray
Requires-Dist: numpy
Requires-Dist: scikit-learn
Requires-Dist: scipy
Requires-Dist: tqdm
Requires-Dist: matplotlib
Requires-Dist: gsw
